ACD_helpers/ACD_shared_functions.py
ACD_helpers/__init__.py
ACD_helpers-0.1.2.dist-info/LICENSE
ACD_helpers-0.1.2.dist-info/METADATA
ACD_helpers-0.1.2.dist-info/WHEEL
ACD_helpers-0.1.2.dist-info/top_level.txt
ACD_helpers-0.1.2.dist-info/RECORD
