Metadata-Version: 2.1
Name: ACD-helpers
Version: 0.1.2
Summary: Helpers; functions that I import all the time.
Home-page: https://github.com/cranedroesch/ACD_helpers
Author: Andrew Crane-Droesch
Author-email: andrew.crane-droesch@pennmedicine.upenn.edu
License: UNKNOWN
Platform: UNKNOWN
Classifier: Programming Language :: Python :: 3
Classifier: License :: OSI Approved :: GNU General Public License v3 or later (GPLv3+)
Classifier: Operating System :: OS Independent
Requires-Python: >=3.6
